dsgbench_ability_calc/__init__.py
dsgbench_ability_calc/ability_scores.py
dsgbench_ability_calc/config.py
dsgbench_ability_calc/data_preprocessing.py
dsgbench_ability_calc/data_processor.py
dsgbench_ability_calc/score_calculator.py
dsgbench_ability_calc/utils.py
dsgbench_ability_calc/pyarmor_runtime_000000/__init__.py
dsgbench_ability_calc/pyarmor_runtime_000000/pyarmor_runtime.pyd
dsgbench_ability_calc/weights/__init__.py
dsgbench_ability_calc/weights/game_weights.py
dsgbench_ability_calc/weights/metrics_range.py
dsgbench_ability_calc/weights/metrics_weights.py
dsgbench_ability_calc/weights/model_abilities.py
dsgbench_ability_calc/weights/scene_ability.py
dsgbench_ability_calc-0.2.0.dist-info/METADATA
dsgbench_ability_calc-0.2.0.dist-info/WHEEL
dsgbench_ability_calc-0.2.0.dist-info/top_level.txt
dsgbench_ability_calc-0.2.0.dist-info/RECORD
