Metadata-Version: 2.1
Name: dsgbench-ability-calc
Version: 0.2.0
Summary: model ability calculation
Author: WenjieTang
Author-email: wenjietang2022@163.com
Requires-Dist: pandas
Requires-Dist: numpy
